eazyml_xai/__init__.py
eazyml_xai/Linux_x86_64/__init__.py
eazyml_xai/Linux_x86_64/eazyml_xai/__init__.cpython-310-x86_64-linux-gnu.so
eazyml_xai/Linux_x86_64/eazyml_xai/__init__.cpython-311-x86_64-linux-gnu.so
eazyml_xai/Linux_x86_64/eazyml_xai/__init__.cpython-312-x86_64-linux-gnu.so
eazyml_xai/Linux_x86_64/eazyml_xai/__init__.cpython-38-x86_64-linux-gnu.so
eazyml_xai/Linux_x86_64/eazyml_xai/__init__.cpython-39-x86_64-linux-gnu.so
eazyml_xai/Linux_x86_64/eazyml_xai/client.cpython-310-x86_64-linux-gnu.so
eazyml_xai/Linux_x86_64/eazyml_xai/client.cpython-311-x86_64-linux-gnu.so
eazyml_xai/Linux_x86_64/eazyml_xai/client.cpython-312-x86_64-linux-gnu.so
eazyml_xai/Linux_x86_64/eazyml_xai/client.cpython-38-x86_64-linux-gnu.so
eazyml_xai/Linux_x86_64/eazyml_xai/client.cpython-39-x86_64-linux-gnu.so
eazyml_xai/Linux_x86_64/eazyml_xai/globals/__init__.cpython-310-x86_64-linux-gnu.so
eazyml_xai/Linux_x86_64/eazyml_xai/globals/__init__.cpython-311-x86_64-linux-gnu.so
eazyml_xai/Linux_x86_64/eazyml_xai/globals/__init__.cpython-312-x86_64-linux-gnu.so
eazyml_xai/Linux_x86_64/eazyml_xai/globals/__init__.cpython-38-x86_64-linux-gnu.so
eazyml_xai/Linux_x86_64/eazyml_xai/globals/__init__.cpython-39-x86_64-linux-gnu.so
eazyml_xai/Linux_x86_64/eazyml_xai/globals/config.cpython-310-x86_64-linux-gnu.so
eazyml_xai/Linux_x86_64/eazyml_xai/globals/config.cpython-311-x86_64-linux-gnu.so
eazyml_xai/Linux_x86_64/eazyml_xai/globals/config.cpython-312-x86_64-linux-gnu.so
eazyml_xai/Linux_x86_64/eazyml_xai/globals/config.cpython-38-x86_64-linux-gnu.so
eazyml_xai/Linux_x86_64/eazyml_xai/globals/config.cpython-39-x86_64-linux-gnu.so
eazyml_xai/Linux_x86_64/eazyml_xai/globals/global_var.cpython-310-x86_64-linux-gnu.so
eazyml_xai/Linux_x86_64/eazyml_xai/globals/global_var.cpython-311-x86_64-linux-gnu.so
eazyml_xai/Linux_x86_64/eazyml_xai/globals/global_var.cpython-312-x86_64-linux-gnu.so
eazyml_xai/Linux_x86_64/eazyml_xai/globals/global_var.cpython-38-x86_64-linux-gnu.so
eazyml_xai-0.0.92.dist-info/LICENSE
eazyml_xai-0.0.92.dist-info/METADATA
eazyml_xai-0.0.92.dist-info/WHEEL
eazyml_xai-0.0.92.dist-info/top_level.txt
eazyml_xai-0.0.92.dist-info/RECORD
