Metadata-Version: 2.2
Name: eazyml-xai
Version: 0.0.92
Summary: eazyml-xai provides APIs for explainable AI (XAI), offering human-readable explanations, feature importance, and predictive reasoning.
Home-page: https://eazyml.com/
Author: EazyML
Author-email: admin@ipsoftlabs.com
Project-URL: Documentation, https://docs.eazyml.com/
Project-URL: Homepage, https://eazyml.com/
Project-URL: Contact Us, https://eazyml.com/trust-in-ai
Project-URL: eazyml-automl, https://pypi.org/project/eazyml-automl/
Project-URL: eazyml-counterfactual, https://pypi.org/project/eazyml-counterfactual/
Project-URL: eazyml-xai, https://pypi.org/project/eazyml-xai/
Project-URL: eazyml-xai-image, https://pypi.org/project/eazyml-xai-image/
Project-URL: eazyml-insight, https://pypi.org/project/eazyml-insight/
Project-URL: eazyml-data-quality, https://pypi.org/project/eazyml-data-quality/
Keywords: xai,explainable-ai,model-explainability,predictive-reasoning,feature-importance,predictive-reasoning,explainability-score,interpretable-ai,local-feature-importance,machine-learning
Classifier: Development Status :: 5 - Production/Stable
Classifier: License :: Other/Proprietary License
Classifier: Intended Audience :: Education
Classifier: Intended Audience :: Developers
Classifier: Intended Audience :: Science/Research
Classifier: Intended Audience :: System Administrators
Classifier: Intended Audience :: Information Technology
Classifier: Programming Language :: Python :: 3.8
Classifier: Programming Language :: Python :: 3.9
Classifier: Programming Language :: Python :: 3.10
Classifier: Programming Language :: Python :: 3.11
Classifier: Programming Language :: Python :: 3.12
Classifier: Topic :: Scientific/Engineering :: Artificial Intelligence
Classifier: Operating System :: Unix
Classifier: Operating System :: MacOS
Classifier: Operating System :: Microsoft :: Windows
Classifier: Operating System :: POSIX :: Linux
Requires-Python: >=3.7
License-File: LICENSE
Requires-Dist: werkzeug>=2.0.3
Requires-Dist: Unidecode
Requires-Dist: pydot
Requires-Dist: cryptography
Requires-Dist: pyyaml
Requires-Dist: urllib3
Requires-Dist: idna
Requires-Dist: tqdm
Requires-Dist: xgboost
Requires-Dist: pandas==1.3.*; python_version <= "3.7"
Requires-Dist: scikit-learn==1.0.*; python_version <= "3.7"
Requires-Dist: numpy==1.21.*; python_version <= "3.7"
Requires-Dist: pandas>=2.0.3; python_version == "3.8"
Requires-Dist: scikit-learn==1.3.*; python_version == "3.8"
Requires-Dist: numpy==1.24.*; python_version == "3.8"
Requires-Dist: pandas>=2.2.3; python_version == "3.9"
Requires-Dist: scikit-learn==1.3.*; python_version == "3.9"
Requires-Dist: numpy==1.24.*; python_version == "3.9"
Requires-Dist: pandas>=2.2.3; python_version == "3.10"
Requires-Dist: scikit-learn==1.3.*; python_version == "3.10"
Requires-Dist: numpy==1.24.*; python_version == "3.10"
Requires-Dist: pandas>=2.2.3; python_version == "3.11"
Requires-Dist: scikit-learn==1.3.*; python_version == "3.11"
Requires-Dist: numpy==1.24.*; python_version == "3.11"
Requires-Dist: pandas>=2.2.3; python_version > "3.11"
Requires-Dist: scikit-learn==1.3.*; python_version > "3.11"
Requires-Dist: numpy; python_version > "3.11"
Dynamic: author
Dynamic: author-email
Dynamic: classifier
Dynamic: description
Dynamic: description-content-type
Dynamic: home-page
Dynamic: keywords
Dynamic: project-url
Dynamic: provides-extra
Dynamic: requires-dist
Dynamic: requires-python
Dynamic: summary
